credit_deposit_calculator/__init__.py
credit_deposit_calculator/calculator.py
credit_deposit_calculator-0.1.2.dist-info/licenses/LICENSE
credit_deposit_calculator-0.1.2.dist-info/METADATA
credit_deposit_calculator-0.1.2.dist-info/WHEEL
credit_deposit_calculator-0.1.2.dist-info/top_level.txt
credit_deposit_calculator-0.1.2.dist-info/RECORD
