Metadata-Version: 2.4
Name: credit_deposit_calculator
Version: 0.1.2
Summary: Kredit va omonatni hisoblash uchun kalkulyator
Home-page: https://github.com/murodalidev/credit_deposit_calculator
Author: Murodali Narzullaev
Author-email: murodalinarzullaevofficial@gmail.com
License: MIT
Classifier: License :: OSI Approved :: MIT License
Classifier: Programming Language :: Python
Classifier: Programming Language :: Python :: 3
Classifier: Programming Language :: Python :: 3.6
Classifier: Programming Language :: Python :: Implementation :: CPython
Classifier: Programming Language :: Python :: Implementation :: PyPy
Requires-Python: >=3.6.0
License-File: LICENSE
Requires-Dist: python-dateutil==2.9.0
Dynamic: author
Dynamic: author-email
Dynamic: classifier
Dynamic: description
Dynamic: description-content-type
Dynamic: home-page
Dynamic: license
Dynamic: license-file
Dynamic: requires-dist
Dynamic: requires-python
Dynamic: summary
